[
  {
    "direction": "FortyFiveUp", 
    "noise": 1, 
    "sysTime": "2016-02-19T13:28:39.043-0800", 
    "xDrip_calculated_value": 150, 
    "xDrip_raw": 149, 
    "dateString": "2016-02-19T13:28:39.043-0800", 
    "sgv": 150, 
    "date": 1455917319043, 
    "xDrip_filtered": 141, 
    "xDrip_age_adjusted_raw_value": 149, 
    "unfiltered": 149000, 
    "rssi": 100, 
    "device": "xDrip-DexcomShare", 
    "filtered": 141000, 
    "xDrip_calculated_current_slope": 1.6659947154647625e-05, 
    "_id": "56c78948a3f298555f026b45", 
    "type": "sgv"
  }, 
  {
    "direction": "FortyFiveUp", 
    "noise": 1, 
    "sysTime": "2016-02-19T13:23:38.922-0800", 
    "xDrip_calculated_value": 145, 
    "xDrip_raw": 145, 
    "dateString": "2016-02-19T13:23:38.922-0800", 
    "sgv": 145, 
    "date": 1455917018922, 
    "xDrip_filtered": 136, 
    "xDrip_age_adjusted_raw_value": 145, 
    "unfiltered": 145000, 
    "rssi": 100, 
    "device": "xDrip-DexcomShare", 
    "filtered": 136000, 
    "xDrip_calculated_current_slope": 3.333322222259259e-05, 
    "_id": "56c787f8a3f298555f026b41", 
    "type": "sgv"
  }, 
  {
    "direction": "FortyFiveUp", 
    "noise": 1, 
    "sysTime": "2016-02-19T13:18:38.921-0800", 
    "xDrip_calculated_value": 135, 
    "xDrip_raw": 138, 
    "dateString": "2016-02-19T13:18:38.921-0800", 
    "sgv": 135, 
    "date": 1455916718921, 
    "xDrip_filtered": 130, 
    "xDrip_age_adjusted_raw_value": 138, 
    "unfiltered": 138000, 
    "rssi": 100, 
    "device": "xDrip-DexcomShare", 
    "filtered": 130000, 
    "xDrip_calculated_current_slope": 3.0063534269088673e-05, 
    "_id": "56c786cca3f298555f026b40", 
    "type": "sgv"
  }, 
  {
    "direction": "FortyFiveUp", 
    "noise": 1, 
    "sysTime": "2016-02-19T13:13:39.555-0800", 
    "xDrip_calculated_value": 126, 
    "xDrip_raw": 132, 
    "dateString": "2016-02-19T13:13:39.555-0800", 
    "sgv": 126, 
    "date": 1455916419555, 
    "xDrip_filtered": 123, 
    "xDrip_age_adjusted_raw_value": 132, 
    "unfiltered": 132000, 
    "rssi": 100, 
    "device": "xDrip-DexcomShare", 
    "filtered": 123000, 
    "xDrip_calculated_current_slope": 2e-05, 
    "_id": "56c785e1a3f298555f026b3f", 
    "type": "sgv"
  }, 
  {
    "direction": "FortyFiveUp", 
    "noise": 1, 
    "sysTime": "2016-02-19T13:08:39.555-0800", 
    "xDrip_calculated_value": 120, 
    "xDrip_raw": 128, 
    "dateString": "2016-02-19T13:08:39.555-0800", 
    "sgv": 120, 
    "date": 1455916119555, 
    "xDrip_filtered": 117, 
    "xDrip_age_adjusted_raw_value": 128, 
    "unfiltered": 128000, 
    "rssi": 100, 
    "device": "xDrip-DexcomShare", 
    "filtered": 117000, 
    "xDrip_calculated_current_slope": 3.666642222385184e-05, 
    "_id": "56c78474a3f298555f026b3c", 
    "type": "sgv"
  }, 
  {
    "direction": "FortyFiveUp", 
    "noise": 1, 
    "sysTime": "2016-02-19T13:03:39.553-0800", 
    "xDrip_calculated_value": 109, 
    "xDrip_raw": 120, 
    "dateString": "2016-02-19T13:03:39.553-0800", 
    "sgv": 109, 
    "date": 1455915819553, 
    "xDrip_filtered": 111, 
    "xDrip_age_adjusted_raw_value": 120, 
    "unfiltered": 120000, 
    "rssi": 100, 
    "device": "xDrip-DexcomShare", 
    "filtered": 111000, 
    "xDrip_calculated_current_slope": 2.3342359045497592e-05, 
    "_id": "56c78346a3f298555f026b38", 
    "type": "sgv"
  }, 
  {
    "direction": "Flat", 
    "noise": 1, 
    "sysTime": "2016-02-19T12:58:39.669-0800", 
    "xDrip_calculated_value": 102, 
    "xDrip_raw": 115, 
    "dateString": "2016-02-19T12:58:39.669-0800", 
    "sgv": 102, 
    "date": 1455915519669, 
    "xDrip_filtered": 107, 
    "xDrip_age_adjusted_raw_value": 115, 
    "unfiltered": 115000, 
    "rssi": 100, 
    "device": "xDrip-DexcomShare", 
    "filtered": 107000, 
    "xDrip_calculated_current_slope": 2.9975919344793015e-05, 
    "_id": "56c7823ba3f298555f026b34", 
    "type": "sgv"
  }, 
  {
    "direction": "Flat", 
    "noise": 1, 
    "sysTime": "2016-02-19T12:53:39.428-0800", 
    "xDrip_calculated_value": 93, 
    "xDrip_raw": 109, 
    "dateString": "2016-02-19T12:53:39.428-0800", 
    "sgv": 93, 
    "date": 1455915219428, 
    "xDrip_filtered": 107, 
    "xDrip_age_adjusted_raw_value": 109, 
    "unfiltered": 109000, 
    "rssi": 100, 
    "device": "xDrip-DexcomShare", 
    "filtered": 107000, 
    "xDrip_calculated_current_slope": 1.6659891644064746e-05, 
    "_id": "56c780efa3f298555f026b2d", 
    "type": "sgv"
  }, 
  {
    "direction": "Flat", 
    "noise": 1, 
    "sysTime": "2016-02-19T12:48:39.306-0800", 
    "xDrip_calculated_value": 88, 
    "xDrip_raw": 106, 
    "dateString": "2016-02-19T12:48:39.306-0800", 
    "sgv": 88, 
    "date": 1455914919306, 
    "xDrip_filtered": 108, 
    "xDrip_age_adjusted_raw_value": 106, 
    "unfiltered": 106000, 
    "rssi": 100, 
    "device": "xDrip-DexcomShare", 
    "filtered": 108000, 
    "xDrip_calculated_current_slope": -3.325120286226354e-06, 
    "_id": "56c77fc2a3f298555f026b29", 
    "type": "sgv"
  }, 
  {
    "direction": "Flat", 
    "noise": 1, 
    "sysTime": "2016-02-19T12:43:38.565-0800", 
    "xDrip_calculated_value": 89, 
    "xDrip_raw": 106, 
    "dateString": "2016-02-19T12:43:38.565-0800", 
    "sgv": 89, 
    "date": 1455914618565, 
    "xDrip_filtered": 110, 
    "xDrip_age_adjusted_raw_value": 106, 
    "unfiltered": 106000, 
    "rssi": 100, 
    "device": "xDrip-DexcomShare", 
    "filtered": 110000, 
    "xDrip_calculated_current_slope": -1.670765611633875e-05, 
    "_id": "56c77eb8a3f298555f026b25", 
    "type": "sgv"
  }
]