[
  {
    "direction": "Flat", 
    "noise": 1, 
    "sysTime": "2016-03-01T02:36:10.476-0800", 
    "xDrip_calculated_value": 176, 
    "xDrip_raw": 173, 
    "dateString": "2016-03-01T02:36:10.476-0800", 
    "sgv": 176, 
    "date": 1456828570476, 
    "xDrip_filtered": 175, 
    "xDrip_age_adjusted_raw_value": 173, 
    "unfiltered": 173000, 
    "rssi": 100, 
    "device": "xDrip-DexcomShare", 
    "filtered": 175000, 
    "xDrip_calculated_current_slope": -6.65088190694086e-06, 
    "_id": "56d570b8a3f298555f028764", 
    "type": "sgv"
  }, 
  {
    "direction": "Flat", 
    "noise": 1, 
    "sysTime": "2016-03-01T02:31:09.764-0800", 
    "xDrip_calculated_value": 178, 
    "xDrip_raw": 175, 
    "dateString": "2016-03-01T02:31:09.764-0800", 
    "sgv": 178, 
    "date": 1456828269764, 
    "xDrip_filtered": 179, 
    "xDrip_age_adjusted_raw_value": 175, 
    "unfiltered": 175000, 
    "rssi": 100, 
    "device": "xDrip-DexcomShare", 
    "filtered": 179000, 
    "xDrip_calculated_current_slope": -3.341899736324111e-06, 
    "_id": "56d56faea3f298555f028760", 
    "type": "sgv"
  }, 
  {
    "direction": "Flat", 
    "noise": 1, 
    "sysTime": "2016-03-01T02:26:10.533-0800", 
    "xDrip_calculated_value": 179, 
    "xDrip_raw": 175, 
    "dateString": "2016-03-01T02:26:10.533-0800", 
    "sgv": 179, 
    "date": 1456827970533, 
    "xDrip_filtered": 182, 
    "xDrip_age_adjusted_raw_value": 175, 
    "unfiltered": 175000, 
    "rssi": 100, 
    "device": "xDrip-DexcomShare", 
    "filtered": 182000, 
    "xDrip_calculated_current_slope": -1.330977503152753e-05, 
    "_id": "56d56e5fa3f298555f02875c", 
    "type": "sgv"
  }, 
  {
    "direction": "Flat", 
    "noise": 1, 
    "sysTime": "2016-03-01T02:21:10.002-0800", 
    "xDrip_calculated_value": 183, 
    "xDrip_raw": 178, 
    "dateString": "2016-03-01T02:21:10.002-0800", 
    "sgv": 183, 
    "date": 1456827670002, 
    "xDrip_filtered": 183, 
    "xDrip_age_adjusted_raw_value": 178, 
    "unfiltered": 178000, 
    "rssi": 100, 
    "device": "xDrip-DexcomShare", 
    "filtered": 183000, 
    "xDrip_calculated_current_slope": -2.6614502242271816e-05, 
    "_id": "56d56d56a3f298555f028758", 
    "type": "sgv"
  }, 
  {
    "direction": "Flat", 
    "noise": 1, 
    "sysTime": "2016-03-01T02:16:09.414-0800", 
    "xDrip_calculated_value": 191, 
    "xDrip_raw": 184, 
    "dateString": "2016-03-01T02:16:09.414-0800", 
    "sgv": 191, 
    "date": 1456827369414, 
    "xDrip_filtered": 182, 
    "xDrip_age_adjusted_raw_value": 184, 
    "unfiltered": 184000, 
    "rssi": 100, 
    "device": "xDrip-DexcomShare", 
    "filtered": 182000, 
    "xDrip_calculated_current_slope": 3.3375943287597168e-06, 
    "_id": "56d56c07a3f298555f028757", 
    "type": "sgv"
  }, 
  {
    "direction": "Flat", 
    "noise": 1, 
    "sysTime": "2016-03-01T02:11:09.797-0800", 
    "xDrip_calculated_value": 190, 
    "xDrip_raw": 183, 
    "dateString": "2016-03-01T02:11:09.797-0800", 
    "sgv": 190, 
    "date": 1456827069797, 
    "xDrip_filtered": 180, 
    "xDrip_age_adjusted_raw_value": 183, 
    "unfiltered": 183000, 
    "rssi": 100, 
    "device": "xDrip-DexcomShare", 
    "filtered": 180000, 
    "xDrip_calculated_current_slope": 9.98508893385877e-06, 
    "_id": "56d56afda3f298555f028756", 
    "type": "sgv"
  }, 
  {
    "direction": "Flat", 
    "noise": 1, 
    "sysTime": "2016-03-01T02:06:09.349-0800", 
    "xDrip_calculated_value": 187, 
    "xDrip_raw": 181, 
    "dateString": "2016-03-01T02:06:09.349-0800", 
    "sgv": 187, 
    "date": 1456826769349, 
    "xDrip_filtered": 177, 
    "xDrip_age_adjusted_raw_value": 181, 
    "unfiltered": 181000, 
    "rssi": 100, 
    "device": "xDrip-DexcomShare", 
    "filtered": 177000, 
    "xDrip_calculated_current_slope": 1.00611044409715e-05, 
    "_id": "56d569afa3f298555f028752", 
    "type": "sgv"
  }, 
  {
    "direction": "Flat", 
    "noise": 1, 
    "sysTime": "2016-03-01T02:01:11.171-0800", 
    "xDrip_calculated_value": 184, 
    "xDrip_raw": 179, 
    "dateString": "2016-03-01T02:01:11.171-0800", 
    "sgv": 184, 
    "date": 1456826471171, 
    "xDrip_filtered": 175, 
    "xDrip_age_adjusted_raw_value": 179, 
    "unfiltered": 179000, 
    "rssi": 100, 
    "device": "xDrip-DexcomShare", 
    "filtered": 175000, 
    "xDrip_calculated_current_slope": 9.998300288950879e-06, 
    "_id": "56d56882a3f298555f028751", 
    "type": "sgv"
  }, 
  {
    "direction": "Flat", 
    "noise": 1, 
    "sysTime": "2016-03-01T01:56:11.120-0800", 
    "xDrip_calculated_value": 181, 
    "xDrip_raw": 176, 
    "dateString": "2016-03-01T01:56:11.120-0800", 
    "sgv": 181, 
    "date": 1456826171120, 
    "xDrip_filtered": 173, 
    "xDrip_age_adjusted_raw_value": 176, 
    "unfiltered": 176000, 
    "rssi": 100, 
    "device": "xDrip-DexcomShare", 
    "filtered": 173000, 
    "xDrip_calculated_current_slope": 1.3336178384722074e-05, 
    "_id": "56d56779a3f298555f028750", 
    "type": "sgv"
  }, 
  {
    "direction": "Flat", 
    "noise": 1, 
    "sysTime": "2016-03-01T01:51:11.184-0800", 
    "xDrip_calculated_value": 177, 
    "xDrip_raw": 174, 
    "dateString": "2016-03-01T01:51:11.184-0800", 
    "sgv": 177, 
    "date": 1456825871184, 
    "xDrip_filtered": 171, 
    "xDrip_age_adjusted_raw_value": 174, 
    "unfiltered": 174000, 
    "rssi": 100, 
    "device": "xDrip-DexcomShare", 
    "filtered": 171000, 
    "xDrip_calculated_current_slope": 6.668111424141897e-06, 
    "_id": "56d56629a3f298555f02874f", 
    "type": "sgv"
  }
]