[
  {
    "direction": "Flat", 
    "noise": 1, 
    "sysTime": "2016-02-27T02:53:12.747-0800", 
    "xDrip_calculated_value": 107, 
    "xDrip_raw": 127, 
    "dateString": "2016-02-27T02:53:12.747-0800", 
    "sgv": 107, 
    "date": 1456570392747, 
    "xDrip_filtered": 130, 
    "xDrip_age_adjusted_raw_value": 127, 
    "unfiltered": 127000, 
    "rssi": 100, 
    "device": "xDrip-DexcomShare", 
    "filtered": 130000, 
    "xDrip_calculated_current_slope": -3.3288283190082756e-06, 
    "_id": "56d18035a3f298555f027f4b", 
    "type": "sgv"
  }, 
  {
    "direction": "Flat", 
    "noise": 1, 
    "sysTime": "2016-02-27T02:48:12.341-0800", 
    "xDrip_calculated_value": 108, 
    "xDrip_raw": 128, 
    "dateString": "2016-02-27T02:48:12.341-0800", 
    "sgv": 108, 
    "date": 1456570092341, 
    "xDrip_filtered": 132, 
    "xDrip_age_adjusted_raw_value": 128, 
    "unfiltered": 128000, 
    "rssi": 100, 
    "device": "xDrip-DexcomShare", 
    "filtered": 132000, 
    "xDrip_calculated_current_slope": -1.0002167136212846e-05, 
    "_id": "56d17f08a3f298555f027f47", 
    "type": "sgv"
  }, 
  {
    "direction": "Flat", 
    "noise": 1, 
    "sysTime": "2016-02-27T02:43:12.406-0800", 
    "xDrip_calculated_value": 111, 
    "xDrip_raw": 130, 
    "dateString": "2016-02-27T02:43:12.406-0800", 
    "sgv": 111, 
    "date": 1456569792406, 
    "xDrip_filtered": 135, 
    "xDrip_age_adjusted_raw_value": 130, 
    "unfiltered": 130000, 
    "rssi": 100, 
    "device": "xDrip-DexcomShare", 
    "filtered": 135000, 
    "xDrip_calculated_current_slope": -1.333120034127873e-05, 
    "_id": "56d17e00a3f298555f027f43", 
    "type": "sgv"
  }, 
  {
    "direction": "Flat", 
    "noise": 1, 
    "sysTime": "2016-02-27T02:38:12.358-0800", 
    "xDrip_calculated_value": 115, 
    "xDrip_raw": 133, 
    "dateString": "2016-02-27T02:38:12.358-0800", 
    "sgv": 115, 
    "date": 1456569492358, 
    "xDrip_filtered": 137, 
    "xDrip_age_adjusted_raw_value": 133, 
    "unfiltered": 133000, 
    "rssi": 100, 
    "device": "xDrip-DexcomShare", 
    "filtered": 137000, 
    "xDrip_calculated_current_slope": -9.998366933400878e-06, 
    "_id": "56d17cb0a3f298555f027f3f", 
    "type": "sgv"
  }, 
  {
    "direction": "Flat", 
    "noise": 1, 
    "sysTime": "2016-02-27T02:33:12.309-0800", 
    "xDrip_calculated_value": 118, 
    "xDrip_raw": 136, 
    "dateString": "2016-02-27T02:33:12.309-0800", 
    "sgv": 118, 
    "date": 1456569192309, 
    "xDrip_filtered": 138, 
    "xDrip_age_adjusted_raw_value": 136, 
    "unfiltered": 136000, 
    "rssi": 100, 
    "device": "xDrip-DexcomShare", 
    "filtered": 138000, 
    "xDrip_calculated_current_slope": -6.6635348053081715e-06, 
    "_id": "56d17b84a3f298555f027f3b", 
    "type": "sgv"
  }, 
  {
    "direction": "Flat", 
    "noise": 1, 
    "sysTime": "2016-02-27T02:28:12.168-0800", 
    "xDrip_calculated_value": 120, 
    "xDrip_raw": 138, 
    "dateString": "2016-02-27T02:28:12.168-0800", 
    "sgv": 120, 
    "date": 1456568892168, 
    "xDrip_filtered": 138, 
    "xDrip_age_adjusted_raw_value": 138, 
    "unfiltered": 138000, 
    "rssi": 100, 
    "device": "xDrip-DexcomShare", 
    "filtered": 138000, 
    "xDrip_calculated_current_slope": 3.3328667319908545e-06, 
    "_id": "56d17a7aa3f298555f027f3a", 
    "type": "sgv"
  }, 
  {
    "direction": "Flat", 
    "noise": 1, 
    "sysTime": "2016-02-27T02:23:12.126-0800", 
    "xDrip_calculated_value": 119, 
    "xDrip_raw": 137, 
    "dateString": "2016-02-27T02:23:12.126-0800", 
    "sgv": 119, 
    "date": 1456568592126, 
    "xDrip_filtered": 138, 
    "xDrip_age_adjusted_raw_value": 137, 
    "unfiltered": 137000, 
    "rssi": 100, 
    "device": "xDrip-DexcomShare", 
    "filtered": 138000, 
    "xDrip_calculated_current_slope": -6.665444668477446e-06, 
    "_id": "56d1792ba3f298555f027f36", 
    "type": "sgv"
  }, 
  {
    "direction": "Flat", 
    "noise": 1, 
    "sysTime": "2016-02-27T02:18:12.071-0800", 
    "xDrip_calculated_value": 121, 
    "xDrip_raw": 139, 
    "dateString": "2016-02-27T02:18:12.071-0800", 
    "sgv": 121, 
    "date": 1456568292071, 
    "xDrip_filtered": 138, 
    "xDrip_age_adjusted_raw_value": 139, 
    "unfiltered": 139000, 
    "rssi": 100, 
    "device": "xDrip-DexcomShare", 
    "filtered": 138000, 
    "xDrip_calculated_current_slope": 0, 
    "_id": "56d177ffa3f298555f027f32", 
    "type": "sgv"
  }, 
  {
    "direction": "Flat", 
    "noise": 1, 
    "sysTime": "2016-02-27T02:13:12.137-0800", 
    "xDrip_calculated_value": 121, 
    "xDrip_raw": 138, 
    "dateString": "2016-02-27T02:13:12.137-0800", 
    "sgv": 121, 
    "date": 1456567992137, 
    "xDrip_filtered": 136, 
    "xDrip_age_adjusted_raw_value": 138, 
    "unfiltered": 138000, 
    "rssi": 100, 
    "device": "xDrip-DexcomShare", 
    "filtered": 136000, 
    "xDrip_calculated_current_slope": 6.672471717060509e-06, 
    "_id": "56d176f5a3f298555f027f31", 
    "type": "sgv"
  }, 
  {
    "direction": "Flat", 
    "noise": 1, 
    "sysTime": "2016-02-27T02:08:12.398-0800", 
    "xDrip_calculated_value": 119, 
    "xDrip_raw": 137, 
    "dateString": "2016-02-27T02:08:12.398-0800", 
    "sgv": 119, 
    "date": 1456567692398, 
    "xDrip_filtered": 135, 
    "xDrip_age_adjusted_raw_value": 137, 
    "unfiltered": 137000, 
    "rssi": 100, 
    "device": "xDrip-DexcomShare", 
    "filtered": 135000, 
    "xDrip_calculated_current_slope": 6.675611986728883e-06, 
    "_id": "56d175a7a3f298555f027f30", 
    "type": "sgv"
  }
]