[
  {
    "filtered": 162000, 
    "direction": "FortyFiveDown", 
    "noise": 1, 
    "raw": 137, 
    "type": "sgv", 
    "_id": "56d30e9ea3f298555f028279", 
    "sysTime": "2016-02-28T07:13:08.055-0800", 
    "dateString": "2016-02-28T07:13:08.055-0800", 
    "sgv": 144, 
    "device": "xDrip-DexcomShare", 
    "xDrip_filtered": 162, 
    "unfiltered": 156000, 
    "xDrip_raw": 156, 
    "date": 1456672388055, 
    "rssi": 100, 
    "xDrip_calculated_current_slope": -1.666400042659841e-05, 
    "xDrip_age_adjusted_raw_value": 156, 
    "xDrip_calculated_value": 144
  }, 
  {
    "filtered": 166000, 
    "direction": "FortyFiveDown", 
    "noise": 1, 
    "raw": 142, 
    "type": "sgv", 
    "_id": "56d30d93a3f298555f028278", 
    "sysTime": "2016-02-28T07:08:08.007-0800", 
    "dateString": "2016-02-28T07:08:08.007-0800", 
    "sgv": 149, 
    "device": "xDrip-DexcomShare", 
    "xDrip_filtered": 166, 
    "unfiltered": 160000, 
    "xDrip_raw": 160, 
    "date": 1456672088007, 
    "rssi": 100, 
    "xDrip_calculated_current_slope": -1.6676617048172077e-05, 
    "xDrip_age_adjusted_raw_value": 160, 
    "xDrip_calculated_value": 149
  }, 
  {
    "filtered": 171000, 
    "direction": "FortyFiveDown", 
    "noise": 1, 
    "raw": 146, 
    "type": "sgv", 
    "_id": "56d30c46a3f298555f028274", 
    "sysTime": "2016-02-28T07:03:08.186-0800", 
    "dateString": "2016-02-28T07:03:08.186-0800", 
    "sgv": 154, 
    "device": "xDrip-DexcomShare", 
    "xDrip_filtered": 171, 
    "unfiltered": 164000, 
    "xDrip_raw": 164, 
    "date": 1456671788186, 
    "rssi": 100, 
    "xDrip_calculated_current_slope": -1.995058904114144e-05, 
    "xDrip_age_adjusted_raw_value": 164, 
    "xDrip_calculated_value": 154
  }, 
  {
    "filtered": 176000, 
    "direction": "FortyFiveDown", 
    "noise": 1, 
    "raw": 152, 
    "type": "sgv", 
    "_id": "56d30b19a3f298555f028273", 
    "sysTime": "2016-02-28T06:58:07.443-0800", 
    "dateString": "2016-02-28T06:58:07.443-0800", 
    "sgv": 160, 
    "device": "xDrip-DexcomShare", 
    "xDrip_filtered": 176, 
    "unfiltered": 169000, 
    "xDrip_raw": 169, 
    "date": 1456671487443, 
    "rssi": 100, 
    "xDrip_calculated_current_slope": -2.3286992218817884e-05, 
    "xDrip_age_adjusted_raw_value": 169, 
    "xDrip_calculated_value": 160
  }, 
  {
    "filtered": 180000, 
    "direction": "FortyFiveDown", 
    "noise": 1, 
    "raw": 159, 
    "type": "sgv", 
    "_id": "56d30a0ea3f298555f028272", 
    "sysTime": "2016-02-28T06:53:06.846-0800", 
    "dateString": "2016-02-28T06:53:06.846-0800", 
    "sgv": 167, 
    "device": "xDrip-DexcomShare", 
    "xDrip_filtered": 180, 
    "unfiltered": 173000, 
    "xDrip_raw": 173, 
    "date": 1456671186846, 
    "rssi": 100, 
    "xDrip_calculated_current_slope": -2.3407535219980672e-05, 
    "xDrip_age_adjusted_raw_value": 173, 
    "xDrip_calculated_value": 167
  }, 
  {
    "filtered": 185000, 
    "direction": "FortyFiveDown", 
    "noise": 1, 
    "raw": 167, 
    "type": "sgv", 
    "_id": "56d308c1a3f298555f028271", 
    "sysTime": "2016-02-28T06:48:07.797-0800", 
    "dateString": "2016-02-28T06:48:07.797-0800", 
    "sgv": 174, 
    "device": "xDrip-DexcomShare", 
    "xDrip_filtered": 185, 
    "unfiltered": 179000, 
    "xDrip_raw": 179, 
    "date": 1456670887797, 
    "rssi": 100, 
    "xDrip_calculated_current_slope": -1.6666444447407367e-05, 
    "xDrip_age_adjusted_raw_value": 179, 
    "xDrip_calculated_value": 174
  }, 
  {
    "filtered": 190000, 
    "direction": "Flat", 
    "noise": 1, 
    "raw": 169, 
    "type": "sgv", 
    "_id": "56d30794a3f298555f028270", 
    "sysTime": "2016-02-28T06:43:07.793-0800", 
    "dateString": "2016-02-28T06:43:07.793-0800", 
    "sgv": 179, 
    "device": "xDrip-DexcomShare", 
    "xDrip_filtered": 190, 
    "unfiltered": 182000, 
    "xDrip_raw": 182, 
    "date": 1456670587793, 
    "rssi": 100, 
    "xDrip_calculated_current_slope": -1.3300879188114335e-05, 
    "xDrip_age_adjusted_raw_value": 182, 
    "xDrip_calculated_value": 179
  }, 
  {
    "filtered": 193000, 
    "direction": "Flat", 
    "noise": 1, 
    "raw": 175, 
    "type": "sgv", 
    "_id": "56d30688a3f298555f02826f", 
    "sysTime": "2016-02-28T06:38:07.061-0800", 
    "dateString": "2016-02-28T06:38:07.061-0800", 
    "sgv": 183, 
    "device": "xDrip-DexcomShare", 
    "xDrip_filtered": 193, 
    "unfiltered": 186000, 
    "xDrip_raw": 186, 
    "date": 1456670287061, 
    "rssi": 100, 
    "xDrip_calculated_current_slope": -3.0095603701090463e-05, 
    "xDrip_age_adjusted_raw_value": 186, 
    "xDrip_calculated_value": 183
  }, 
  {
    "filtered": 195000, 
    "direction": "Flat", 
    "noise": 1, 
    "raw": 189, 
    "type": "sgv", 
    "_id": "56d30541a3f298555f02826e", 
    "sysTime": "2016-02-28T06:33:08.014-0800", 
    "dateString": "2016-02-28T06:33:08.014-0800", 
    "sgv": 192, 
    "device": "xDrip-DexcomShare", 
    "xDrip_filtered": 195, 
    "unfiltered": 193000, 
    "xDrip_raw": 193, 
    "date": 1456669988014, 
    "rssi": 100, 
    "xDrip_calculated_current_slope": -3.3328000853196824e-06, 
    "xDrip_age_adjusted_raw_value": 193, 
    "xDrip_calculated_value": 192
  }, 
  {
    "filtered": 193000, 
    "direction": "Flat", 
    "noise": 1, 
    "raw": 194, 
    "type": "sgv", 
    "_id": "56d30415a3f298555f02826d", 
    "sysTime": "2016-02-28T06:28:07.966-0800", 
    "dateString": "2016-02-28T06:28:07.966-0800", 
    "sgv": 193, 
    "device": "xDrip-DexcomShare", 
    "xDrip_filtered": 193, 
    "unfiltered": 194000, 
    "xDrip_raw": 194, 
    "date": 1456669687966, 
    "rssi": 100, 
    "xDrip_calculated_current_slope": 3.329005626019508e-06, 
    "xDrip_age_adjusted_raw_value": 194, 
    "xDrip_calculated_value": 193
  }
]