{
  "device": "openaps://indy-e1", 
  "pump": {
    "battery": {
      "status": "normal", 
      "voltage": 1.57
    }, 
    "status": {
      "status": "normal", 
      "timestamp": "2016-02-17T02:44:43.000Z", 
      "bolusing": false, 
      "suspended": false
    }, 
    "reservoir": 86.725, 
    "clock": "2016-02-16T18:44:15-08:00"
  }, 
  "openaps": {
    "suggested": {
      "bg": 96, 
      "temp": "absolute", 
      "snoozeBG": 63, 
      "timestamp": "2016-02-17T02:42:50.000Z", 
      "rate": 0, 
      "reason": "Eventual BG 26<110, Snooze BG 63, setting -1.66U/hr", 
      "eventualBG": 26, 
      "duration": 30, 
      "mealAssist": "Off: Carbs: 55 Boluses: 1.75 Target: 115 Deviation: 22 BGI: -6.12", 
      "tick": -3
    }, 
    "iob": {
      "netbasalinsulin": -0.4, 
      "timestamp": "2016-02-17T02:42:50.000Z", 
      "basaliob": -0.1, 
      "activity": 0.0153, 
      "bolussnooze": 0.311, 
      "iob": 1.149
    }, 
    "enacted": {
      "requested": {
        "duration": 30, 
        "rate": 0, 
        "temp": "absolute"
      }, 
      "bg": 96, 
      "temp": "absolute", 
      "snoozeBG": 63, 
      "timestamp": "2016-02-17T02:43:02.000Z", 
      "reason": "Eventual BG 26<110, Snooze BG 63, setting -1.66U/hr", 
      "rate": 0, 
      "eventualBG": 26, 
      "recieved": true, 
      "duration": 30, 
      "mealAssist": "Off: Carbs: 55 Boluses: 1.75 Target: 115 Deviation: 22 BGI: -6.12", 
      "tick": -3
    }
  }, 
  "mmtune": {
    "scanDetails": [
      [
        "916.560", 
        5, 
        -61
      ], 
      [
        "916.580", 
        5, 
        -56
      ], 
      [
        "916.600", 
        5, 
        -56
      ], 
      [
        "916.620", 
        5, 
        -58
      ], 
      [
        "916.640", 
        5, 
        -57
      ], 
      [
        "916.660", 
        5, 
        -57
      ], 
      [
        "916.680", 
        5, 
        -59
      ], 
      [
        "916.700", 
        5, 
        -63
      ]
    ], 
    "setFreq": 916.6, 
    "timestamp": "2016-02-17T02:44:22.000Z", 
    "usedDefault": false
  }
}