{
  "device": "openaps://indy-e1", 
  "pump": {
    "battery": {
      "status": "normal", 
      "voltage": 1.57
    }, 
    "status": {
      "status": "normal", 
      "timestamp": "2016-02-16T18:13:52.000Z", 
      "bolusing": false, 
      "suspended": false
    }, 
    "reservoir": 93.3, 
    "clock": "2016-02-16T10:13:24-08:00"
  }, 
  "openaps": {
    "suggested": {
      "bg": 101, 
      "temp": "absolute", 
      "snoozeBG": 115, 
      "timestamp": "2016-02-16T18:12:51.000Z", 
      "reason": "115 is in range. No temp required", 
      "eventualBG": 115, 
      "mealAssist": "Off: Carbs: 24 Boluses: 2.4 Target: 115 Deviation: 21 BGI: -4.84", 
      "tick": "+3"
    }, 
    "iob": {
      "netbasalinsulin": -0.5, 
      "timestamp": "2016-02-16T18:12:50.000Z", 
      "basaliob": -0.365, 
      "activity": 0.0121, 
      "bolussnooze": 0, 
      "iob": 0.093
    }, 
    "enacted": {
      "requested": {
        "duration": 0, 
        "rate": 0, 
        "temp": "absolute"
      }, 
      "bg": 98, 
      "temp": "absolute", 
      "snoozeBG": 106, 
      "timestamp": "2016-02-16T18:08:50.000Z", 
      "reason": "Eventual BG 106<110, but Delta +3 > Exp. Delta -5.2; cancel", 
      "rate": 0, 
      "eventualBG": 106, 
      "recieved": true, 
      "duration": 0, 
      "mealAssist": "Off: Carbs: 24 Boluses: 2.4 Target: 115 Deviation: 20 BGI: -5.48", 
      "tick": "+3"
    }
  }, 
  "mmtune": {
    "scanDetails": [
      [
        "916.560", 
        3, 
        -95
      ], 
      [
        "916.580", 
        5, 
        -90
      ], 
      [
        "916.600", 
        5, 
        -76
      ], 
      [
        "916.620", 
        5, 
        -73
      ], 
      [
        "916.640", 
        5, 
        -76
      ], 
      [
        "916.660", 
        5, 
        -79
      ], 
      [
        "916.680", 
        4, 
        -80
      ], 
      [
        "916.700", 
        5, 
        -77
      ], 
      [
        "916.720", 
        1, 
        -97
      ]
    ], 
    "setFreq": 916.62, 
    "timestamp": "2016-02-16T18:13:32.000Z", 
    "usedDefault": false
  }
}