{
  "device": "openaps://indy-e1", 
  "pump": {
    "battery": {
      "status": "normal", 
      "voltage": 1.57
    }, 
    "status": {
      "status": "normal", 
      "timestamp": "2016-02-22T04:20:39.000Z", 
      "bolusing": false, 
      "suspended": false
    }, 
    "reservoir": 97.65, 
    "clock": "2016-02-21T20:20:12-08:00"
  }, 
  "openaps": {
    "suggested": {
      "bg": 94, 
      "temp": "absolute", 
      "snoozeBG": 94, 
      "timestamp": "2016-02-22T04:21:52.000Z", 
      "rate": 0.6, 
      "reason": "30m@-0.700 = -0.350 < req -0.05-0.2U", 
      "eventualBG": 94, 
      "duration": 30, 
      "mealAssist": "Off: Carbs: 90 Boluses: 3.2 Target: 115 Deviation: 28 BGI: -10.2", 
      "tick": "+2"
    }, 
    "iob": {
      "netbasalinsulin": -0.4, 
      "timestamp": "2016-02-22T04:21:51.000Z", 
      "basaliob": -0.444, 
      "activity": 0.0255, 
      "bolussnooze": 0, 
      "iob": 0.351
    }, 
    "enacted": {
      "requested": {
        "duration": 30, 
        "rate": 0.6, 
        "temp": "absolute"
      }, 
      "bg": 94, 
      "temp": "absolute", 
      "snoozeBG": 94, 
      "timestamp": "2016-02-22T04:22:03.000Z", 
      "reason": "30m@-0.700 = -0.350 < req -0.05-0.2U", 
      "rate": 0.575, 
      "eventualBG": 94, 
      "recieved": true, 
      "duration": 30, 
      "mealAssist": "Off: Carbs: 90 Boluses: 3.2 Target: 115 Deviation: 28 BGI: -10.2", 
      "tick": "+2"
    }
  }, 
  "mmtune": {
    "scanDetails": [
      [
        "916.560", 
        5, 
        -92
      ], 
      [
        "916.580", 
        5, 
        -88
      ], 
      [
        "916.600", 
        5, 
        -87
      ], 
      [
        "916.620", 
        5, 
        -88
      ], 
      [
        "916.640", 
        5, 
        -88
      ], 
      [
        "916.660", 
        5, 
        -88
      ], 
      [
        "916.680", 
        5, 
        -89
      ], 
      [
        "916.700", 
        4, 
        -95
      ]
    ], 
    "setFreq": 916.6, 
    "timestamp": "2016-02-22T04:20:22.000Z", 
    "usedDefault": false
  }
}