{
  "device": "openaps://indy-e1", 
  "pump": {
    "battery": {
      "status": "normal", 
      "voltage": 1.56
    }, 
    "status": {
      "status": "normal", 
      "timestamp": "2016-03-05T08:13:29.000Z", 
      "bolusing": false, 
      "suspended": false
    }, 
    "reservoir": 124.85, 
    "clock": "2016-03-05T00:13:07-08:00"
  }, 
  "openaps": {
    "suggested": {
      "bg": 128, 
      "temp": "absolute", 
      "snoozeBG": 115, 
      "timestamp": "2016-03-05T08:12:14.000Z", 
      "rate": 0, 
      "reason": "115 is in range. No temp required; cancel", 
      "eventualBG": 115, 
      "duration": 0, 
      "mealAssist": "Off: Carbs: 0 Boluses: 0.3 Target: 115 Deviation: 11 BGI: -1.64", 
      "tick": "+6"
    }, 
    "iob": {
      "netbasalinsulin": 0.4, 
      "timestamp": "2016-03-05T08:12:13.000Z", 
      "basaliob": 0.288, 
      "activity": 0.0041, 
      "bolussnooze": 0, 
      "iob": 0.304
    }, 
    "enacted": {
      "requested": {
        "duration": 0, 
        "rate": 0, 
        "temp": "absolute"
      }, 
      "bg": 128, 
      "temp": "absolute", 
      "snoozeBG": 115, 
      "timestamp": "2016-03-05T08:12:38.000Z", 
      "reason": "115 is in range. No temp required; cancel", 
      "rate": 0, 
      "eventualBG": 115, 
      "recieved": true, 
      "duration": 0, 
      "mealAssist": "Off: Carbs: 0 Boluses: 0.3 Target: 115 Deviation: 11 BGI: -1.64", 
      "tick": "+6"
    }
  }, 
  "mmtune": {
    "scanDetails": [
      [
        "916.560", 
        5, 
        -92
      ], 
      [
        "916.580", 
        5, 
        -84
      ], 
      [
        "916.600", 
        5, 
        -82
      ], 
      [
        "916.620", 
        5, 
        -81
      ], 
      [
        "916.640", 
        5, 
        -81
      ], 
      [
        "916.660", 
        5, 
        -81
      ], 
      [
        "916.680", 
        4, 
        -86
      ], 
      [
        "916.700", 
        4, 
        -87
      ], 
      [
        "916.720", 
        5, 
        -92
      ]
    ], 
    "setFreq": 916.66, 
    "timestamp": "2016-03-05T08:13:22.000Z", 
    "usedDefault": false
  }
}